README.md
setup.cfg
setup.py
re_map/__init__.py
re_map/core.py
re_map/slow.py
re_map/utils.py
re_map.egg-info/PKG-INFO
re_map.egg-info/SOURCES.txt
re_map.egg-info/dependency_links.txt
re_map.egg-info/top_level.txt
tests/__init__.py
tests/test_bundled_modifiers.py
tests/test_intersecting_groups.py
tests/test_matching_groups.py
tests/test_other.py
tests/test_single_modifier.py