Metadata-Version: 2.1
Name: re-map
Version: 0.4.6
Summary: Apply multiple regex patterns and keep change index map.
Home-page: https://github.com/aleksas/re-map
Author: Aleksas Pielikis
Author-email: ant.kampo@gmail.com
License: UNKNOWN
Platform: UNKNOWN
Classifier: Programming Language :: Python :: 3
Classifier: License :: OSI Approved :: MIT License
Classifier: Operating System :: OS Independent
Requires-Python: >=2.7
